{
  "continents": {
    "North America": {},
    "South America": {},
    "Europe": {},
    "Asia": {},
    "Africa": {},
    "Oceania": {},
    "Antarctica": {}
  },
  "countries": {
    "United States": {
      "continent": "North America"
    },
    "Mexico": {
      "continent": "North America"
    },
    "Australia": {
      "continent": "Oceania"
    },
    "Germany": {
      "continent": "Europe"
    },
    "Norway": {
      "continent": "Europe"
    },
    "Sweden": {
      "continent": "Europe"
    },
    "Canada": {
      "continent": "North America"
    },
    "Colombia": {
      "continent": "South America"
    },
    "Argentina": {
      "continent": "South America"
    },
    "Philippines": {
      "continent": "Asia"
    },
    "Indonesia": {
      "continent": "Asia"
    },
    "United Kingdom": {
      "continent": "Europe"
    },
    "Czech Republic": {
      "continent": "Europe"
    },
    "New Zealand": {
      "continent": "Oceania"
    }
  },
  "states": {
    "Arizona": {
      "continent": "North America",
      "country": "United States"
    },
    "Texas": {
      "continent": "North America",
      "country": "United States"
    },
    "California": {
      "continent": "North America",
      "country": "United States"
    },
    "New Mexico": {
      "continent": "North America",
      "country": "United States"
    },
    "Ohio": {
      "continent": "North America",
      "country": "United States"
    },
    "Pennsylvania": {
      "continent": "North America",
      "country": "United States"
    },
    "Bavaria": {
      "continent": "Europe",
      "country": "Germany"
    },
    "Oregon": {
      "continent": "North America",
      "country": "United States"
    },
    "New York": {
      "continent": "North America",
      "country": "United States"
    },
    "Massachusetts": {
      "continent": "North America",
      "country": "United States"
    },
    "Banten": {
      "continent": "Asia",
      "country": "Indonesia"
    },
    "New Jersey": {
      "continent": "North America",
      "country": "United States"
    },
    "New Hampshire": {
      "continent": "North America",
      "country": "United States"
    },
    "Connecticut": {
      "continent": "North America",
      "country": "United States"
    },
    "Vasdø": {
      "continent": "Europe",
      "country": "Norway"
    },
    "Queensland": {
      "continent": "Oceania",
      "country": "Australia"
    },
    "London": {
      "continent": "Europe",
      "country": "United Kingdom"
    },
    "Tasmania": {
      "continent": "Oceania",
      "country": "Australia"
    }
  },
  "cities": {
    "Phoenix": {
      "continent": "North America",
      "country": "United States",
      "state": "Arizona"
    },
    "Glendale": {
      "continent": "North America",
      "country": "United States",
      "state": "Arizona"
    },
    "Surprise": {
      "continent": "North America",
      "country": "United States",
      "state": "Arizona"
    },
    "Buckeye": {
      "continent": "North America",
      "country": "United States",
      "state": "Arizona"
    },
    "Portland": {
      "continent": "North America",
      "country": "United States",
      "state": "Oregon"
    },
    "Los Angeles": {
      "continent": "North America",
      "country": "United States",
      "state": "California"
    },
    "Ontario": {
      "continent": "North America",
      "country": "United States",
      "state": "California"
    },
    "Munich": {
      "continent": "Europe",
      "country": "Germany",
      "state": "Bavaria"
    }
  },
  "links": {
    "north america": {
      "continent": "North America"
    },
    "na": {
      "continent": "North America"
    },
    "sa": {
      "continent": "South America"
    },
    "south america": {
      "continent": "South America"
    },
    "eu": {
      "continent": "Europe"
    },
    "europe": {
      "continent": "Europe"
    },
    "africa": {
      "continent": "Africa"
    },
    "asia": {
      "continent": "Asia"
    },
    "oceania": {
      "continent": "Oceania"
    },
    "australia": {
      "continent": "Australia"
    },
    "antarctica": {
      "continent": "Antarctica"
    },
    "us": {
      "country": "United States"
    },
    "usa": {
      "country": "United States"
    },
    "united states": {
      "country": "United States"
    },
    "united states of america": {
      "country": "United States"
    },
    "america": {
      "country": "United States"
    },
    "au": {
      "country": "Australia"
    },
    "australia": {
      "country": "Australia"
    },
    "germany": {
      "country": "Germany"
    },
    "german": {
      "country": "Germany"
    },
    "norway": {
      "country": "Norway"
    },
    "canada": {
      "country": "Canada"
    },
    "colombia": {
      "country": "Colombia"
    },
    "philippines": {
      "country": "Philippines"
    },
    "indonesia": {
      "country": "Indonesia"
    },
    "sweden": {
      "country": "Sweden"
    },
    "mexico": {
      "country": "Mexico"
    },
    "argentina": {
      "country": "Argentina"
    },
    "nz": {
      "country": "New Zealand"
    },
    "new zealand": {
      "country": "New Zealand"
    },
    "czech": {
      "country": "Czech Republic"
    },
    "czechoslovakia": {
      "country": "Czech Republic"
    },
    "czech republic": {
      "country": "Czech Republic"
    },
    "uk": {
      "country": "United Kingdom"
    },
    "gb": {
      "country": "United Kingdom"
    },
    "britain": {
      "country": "United Kingdom"
    },
    "britian": {
      "country": "United Kingdom"
    },
    "united kingdom": {
      "country": "United Kingdom"
    },
    "great britain": {
      "country": "United Kingdom"
    },
    "az": {
      "state": "Arizona"
    },
    "arizona": {
      "state": "Arizona"
    },
    "tx": {
      "state": "Texas"
    },
    "texas": {
      "state": "Texas"
    },
    "ca": {
      "state": "California"
    },
    "california": {
      "state": "California"
    },
    "or": {
      "state": "Oregon"
    },
    "oregon": {
      "state": "Oregon"
    },
    "nm": {
      "state": "New Mexico"
    },
    "new mexico": {
      "state": "New Mexico"
    },
    "oh": {
      "state": "Ohio"
    },
    "ohio": {
      "state": "Ohio"
    },
    "pa": {
      "state": "Pennsylvania"
    },
    "pennsylvania": {
      "state": "Pennsylvania"
    },
    "ny": {
      "state": "New York"
    },
    "new york": {
      "state": "New York"
    },
    "ct": {
      "state": "Connecticut"
    },
    "connecticut": {
      "state": "Connecticut"
    },
    "new hampshire": {
      "state": "New Hampshire"
    },
    "nh": {
      "state": "New Hampshire"
    },
    "nj": {
      "state": "New Jersey"
    },
    "new jersey": {
      "state": "New Jersey"
    },
    "bavaria": {
      "state": "Bavaria"
    },
    "queensland": {
      "state": "Queensland"
    },
    "vasdo": {
      "state": "Vasdø"
    },
    "vasdø": {
      "state": "Vasdø"
    },
    "ma": {
      "state": "Massachusetts"
    },
    "massachusetts": {
      "state": "Massachusetts"
    },
    "tasmania": {
      "state": "Tasmania"
    },
    "la": {
      "city": "Los Angeles"
    },
    "los angeles": {
      "city": "Los Angeles"
    },
    "px": {
      "city": "Phoenix"
    },
    "phoenix": {
      "city": "Phoenix"
    },
    "glendale": {
      "city": "Glendale"
    },
    "surprise": {
      "city": "Surprise"
    },
    "buckeye": {
      "city": "Buckeye"
    },
    "portland": {
      "city": "Portland"
    },
    "ontario": {
      "city": "Ontario"
    },
    "munich": {
      "city": "Munich"
    }
  }
}
